{"cameraMode":{"drawMode":0,"name":"Shaded","section":"Shading Mode"},"sceneLighting":false,"audioPlay":false,"sceneViewState":{"m_AlwaysRefresh":false,"showFog":true,"showSkybox":true,"showFlares":true,"showImageEffects":true,"showParticleSystems":true,"showVisualEffectGraphs":true,"m_FxEnabled":true},"in2DMode":false,"pivot":{"x":1498.5216064453125,"y":-397.672607421875,"z":534.1210327148438},"rotation":{"x":0.10069608688354492,"y":0.5709899067878723,"z":-0.07063481211662293,"w":0.8117859959602356},"size":824.1826171875,"orthographic":false}